[
  {
    "id": "post_1784895391995",
    "ts": 1784895391995,
    "category": "articles",
    "type": "article",
    "icon": "📰",
    "en": {
      "title": "The Dictatorship of the Bourgeoisie or the Dictatorship of the Proletariat?",
      "excerpt": "On the dictatorship of the proletariat and bourgeois \"democracy\".",
      "body": "Since the Great October Revolution, communists have been in the dock before capitalist and liberal forces regarding the concepts of democracy and dictatorship. The liberal, in any discussion of an alternative to the current social order, presents a caricatured image of freedom and democracy to the worker. Like the priesthood of the Abrahamic religions, they warn workers of the demon of socialism and the dictatorship of the proletariat.\n\nThese capitalist suspicions easily dissipate when the communist relies on their own analytical framework to provide a clear picture of the world, free from liberal delusions. Starting with the definition of the concepts, dictatorship is nothing more than the domination of one group over another. In Marxism and texts dedicated to class struggle among revolutionaries, dictatorship is the rule of one class over another, because the goal of communists is for the working class, or the proletariat, to come to power and establish a socialist republic to protect the dictatorship of the proletariat. The state and its apparatus are merely instruments of class rule, differing only in the nature of the class they serve. Therefore, we must begin with this definition and recognize that the defining characteristic of this thesis is the dictatorship of the bourgeoisie, which encompasses republics, liberal representative systems, constitutional monarchies, absolute monarchies, oligarchies, and military regimes. The liberal is enamored with all things capitalist, even if they contradict what he promotes to the public. Are not the despotic and reactionary kingdoms and sultanates of the Arabian Gulf the darlings of the \"democracies\" of Europe, the United States, and Canada?\n\nThe liberal will cunningly attempt to conceal his crimes and the crimes of his ideological predecessors from the era of the Red Scare and McCarthyism, as well as the names of all the individuals, detainees, prisoners, tortured, killed, and martyrs across the globe, numbering in the millions. They were victims and martyrs of global capitalism in all its forms: liberal, reactionary, oligarchic, fascist, and imperialist.\n\nThis is not surprising to us as communists, but it is our duty to expose the foundations of the social order so that it may be destroyed by the revolutionary working class.\n\nDemocracy is not incompatible with the dictatorship of the proletariat. Unlike bourgeois regimes, revolutionaries do not define democracy as merely counting votes every five years to elect a capitalist ruling committee that will impose the will of the capitalist class it represents on society.\n\nThe socialist republic extends democracy to all segments of working-class life, addressing their concerns as workers and citizens within the workers' republic through consultative and participatory democracy. This state amplifies the voices of the oppressed and empowers workers, both men and women, peasants, and all oppressed and suppressed identities. In this way, people’s power is established.\n\nForward for socialism!"
    },
    "fr": {
      "title": "Dictature de la bourgeoisie ou dictature du prolétariat?",
      "excerpt": "Sur la dictature du prolétariat et la « démocratie » bourgeoise.",
      "body": "Depuis la Révolution d'Octobre, les communistes sont confrontés aux forces capitalistes et libérales quant à leurs conceptions de la démocratie et de la dictature. Le libéral, dans toute discussion sur une alternative à l'ordre social établi, présente aux travailleurs une image caricaturale de la liberté et de la démocratie. À l'instar des clergés des religions abrahamiques, il les met en garde contre le démon du socialisme et la dictature du prolétariat.\n\nCes soupçons capitalistes s'estompent aisément lorsque le communiste s'appuie sur son propre cadre d'analyse pour offrir une vision claire du monde, affranchie des illusions libérales. Partant de la définition même de ces concepts, la dictature n'est rien d'autre que la domination d'un groupe sur un autre. Dans le marxisme et les textes consacrés à la lutte des classes chez les révolutionnaires, la dictature est le règne d'une classe sur une autre, car l'objectif des communistes est que la classe ouvrière, ou prolétariat, accède au pouvoir et instaure une république socialiste afin de protéger la dictature du prolétariat. L'État et son appareil ne sont que des instruments de domination de classe, ne différant que par la nature de la classe qu'ils servent. Dès lors, il nous faut partir de cette définition et reconnaître que la caractéristique essentielle de cette thèse est la dictature de la bourgeoisie, qui englobe les républiques, les systèmes représentatifs libéraux, les monarchies constitutionnelles, les monarchies absolues, les oligarchies et les régimes militaires. Le libéral est fasciné par tout ce qui relève du capitalisme, même si cela contredit ce qu'il promeut publiquement. Les royaumes et sultanats despotiques et réactionnaires du Golfe arabique ne sont-ils pas les chouchous des « démocraties » d'Europe, des États-Unis et du Canada ?\n\nLe libéral s'efforcera habilement de dissimuler ses crimes et ceux de ses prédécesseurs idéologiques de l'époque de la chasse aux sorcières anticommuniste et du maccarthysme, ainsi que les noms de tous les individus, détenus, prisonniers, torturés, tués et martyrs à travers le monde, qui se comptent par millions. Ils furent victimes et martyrs du capitalisme mondial sous toutes ses formes : libérale, réactionnaire, oligarchique, fasciste et impérialiste.\n\nCela ne nous surprend pas, nous autres communistes, mais il est de notre devoir de dénoncer les fondements de l'ordre social afin qu'il soit détruit par la classe ouvrière révolutionnaire.\n\nLa démocratie n'est pas incompatible avec la dictature du prolétariat. Contrairement aux régimes bourgeois, les révolutionnaires ne définissent pas la démocratie comme un simple comptage de votes tous les cinq ans pour élire un comité dirigeant capitaliste qui imposera à la société la volonté de la classe capitaliste qu'il représente.\n\nLa république socialiste étend la démocratie à tous les segments de la vie ouvrière, répondant à leurs préoccupations en tant que travailleurs et citoyens au sein de la république ouvrière par le biais d'une démocratie consultative et participative. Cet État amplifie la voix des opprimés et donne du pouvoir aux travailleurs et travailleuses, aux paysans et à toutes les identités opprimées et réprimées. Ainsi s'établit le pouvoir du peuple.\n\nEn avant pour le socialisme!"
    },
    "ar": {
      "title": "ديكتاتورية البرجوازية أم ديكتاتورية البروليتاريا؟",
      "excerpt": "حول ديكتاتورية البروليتاريا و\"الديمقراطية\" البرجوازية.",
      "body": "لطالما كان الشيوعيون منذ ثورة أكتوبر الكبرى في قفص الإتهام أمام القوى الرأسمالية واللبرالية حول مفهومي الديمقراطية والديكتاتورية. يلوح اللبرالي في صورة كاريكاتورية أمام  العامل كعكة الحرية والديمقراطية في أي نقاش عن نظام بديل للنظام الإجتماعي الحالي. وككهنوت الديانات الإبراهيمية، يحذر العمال من شيطان الإشتراكية وديكتاتورية البروليتاريا.\n\nهذه الشبهات الرأسمالية تندثر بسهولة عندما يتكئ الشيوعي على تحليله الماجي ليعطي صورة واضحة للعالم بعيدا عن الهذيان اللبرالي. فبدءا بتعريف المفاهيم، فإن الديكتاتورية ليست إلا هيمنة جماعة على أخرى. ففي الماركسية والنصوص المخصصة للنضال الطبقي عند الثوريين، تكون الديكتاتورية حكم طبقة على أخرى؛ لأن هدف الشيوعيين هو وصول الطبقة العاملة أو البروليتاريا إلى الحكم وإنشاء جمهورية إشتراكية لحماية ديكتاتورية البروليتاريا. فالدولة وأجهزتها لا تكون سوى أدوات للحكم الطبقي، ولا تختلف إلا في طبيعة الطبقة التي تخدمها. \n\nيحتم علينا إذا أن ننطلق من هذا التعريف، ونعي أن نقيد الأطروحة هو ديكتاتورية البرجوازية التي تشمل الجمهوريات والأنظمة التمثيلية اللبرالية والملكيات الدستورية والملكيات المطلقة والألغرشيات والأنظمة العسكرية. فاللبرالي عاشق لكل ما هو رأسمالي، ولو كان في تناقض مع ما كان يسوقه للعامة. فأليست المملكات والسلطنات المستبدة والرجعية بالخليج العربي حبيبة \"ديمقراطيات\" أوروبا والولايات المتحدة الأمريكية وكندا.\n\nسيحاول اللبرالي بمكره أن يستر جرائمه وجرائم أسلافه الأيديولوجيين من حقب الخوف الأحمر والسياسة الماكارثية، وكل أسماء الأفراد والمعتقلين والمسجونين والمعذبين والمقتولين والشهداء في كل أنحاء المعمورة والمعدودين بالملايين. فقد كانوا ضحايا وشهداء الرأسمالية العالمية بكل أطيافها اللبرالية والرجعية والألغرشية والفاشية والإمبريالية.\n\nلا نستغرب ذلك كوننا شيوعيين، لكنه واجبنا أن ننير دعامات النظام الإجتماعي حتى تدمره اليد العاملة الثائرة.\n\nالديمقراطية ليست في تضاد مع ديكتاتورية البروليتاريا. فعلى غرار الأنظمة البرجوازية لا يعرف الثوريون الديمقراطية على أنها محض حساب عدد الأصوات في صندوق كل خمس سنوات لإقتراع لجنة الحكم الرأسمالية التي ستفرض سلكة الفئة الرأسمالية التي تمثلها على المجتمع. \n\nالجمهورية الإشتراكية توسع الديمقراطية إلى جموع أطياف الحياة العمالية في ما يهمه كعامل ومواطن في جمهورية العمال من خلال الديمقراطية الاستشارية والتشاركية. هذه الدولة ترفع أصوات المضطهدين، وتوصل العامل رجلا وإمرأة والفلاح والهويات المضطهدة والمقموعة إلى القوة. وبهذا تتأسس قوة الشعب.\n\nإلى الأمام من أجل الإشتراكية!"
    },
    "author": "Assam ANZBAY",
    "authorAr": "أسام أنزباي",
    "authorPhoto": "images/authors/1784892217092_pfp.png",
    "thumbnailUrl": "images/thumbnails/1784895014345_12345.png",
    "date": "2026-07-24",
    "fileUrl": null
  }
]